ofxstatement_nordigen/__init__.py
ofxstatement_nordigen/plugin.py
ofxstatement_nordigen/schemas.py
ofxstatement_nordigen-0.2.2.dist-info/METADATA
ofxstatement_nordigen-0.2.2.dist-info/WHEEL
ofxstatement_nordigen-0.2.2.dist-info/entry_points.txt
ofxstatement_nordigen-0.2.2.dist-info/top_level.txt
ofxstatement_nordigen-0.2.2.dist-info/RECORD
