Metadata-Version: 2.4
Name: ofxstatement-nordigen
Version: 0.2.2
Summary: ofxstatement plugin for Nordigen bank statements
Author-email: Jimmy Stammers <jimmy.stammers@gmail.com>
Project-URL: Homepage, https://github.com/jstammers/ofxstatement-nordigen/
Keywords: ofx,banking,statement,plugin,ofxstatement
Classifier: Development Status :: 3 - Alpha
Classifier: Programming Language :: Python :: 3
Classifier: Natural Language :: English
Classifier: Topic :: Office/Business :: Financial :: Accounting
Classifier: Topic :: Utilities
Classifier: Environment :: Console
Classifier: Operating System :: OS Independent
Classifier: License :: OSI Approved :: GNU General Public License v3 (GPLv3)
Requires-Python: >=3.12
Requires-Dist: ofxstatement
Requires-Dist: pydantic
Requires-Dist: requests
Requires-Dist: requests-cache
Requires-Dist: wheel>=0.45.1
